setup.py
bmi_ilamb/__init__.py
bmi_ilamb/bmi_ilamb.py
bmi_ilamb/config.py
bmi_ilamb/version.py
bmi_ilamb.egg-info/PKG-INFO
bmi_ilamb.egg-info/SOURCES.txt
bmi_ilamb.egg-info/dependency_links.txt
bmi_ilamb.egg-info/requires.txt
bmi_ilamb.egg-info/top_level.txt
bmi_ilamb/data/basins_0.5x0.5.nc
bmi_ilamb/data/bmi_ilamb.yaml
bmi_ilamb/data/bmi_ilamb_with_build_dir.yaml
bmi_ilamb/data/bmi_ilamb_with_confrontations.yaml
bmi_ilamb/data/bmi_ilamb_with_custom_regions_nc.yaml
bmi_ilamb/data/bmi_ilamb_with_custom_regions_txt.yaml
bmi_ilamb/data/bmi_ilamb_with_models.yaml
bmi_ilamb/data/bmi_ilamb_with_regions_1.yaml
bmi_ilamb/data/bmi_ilamb_with_regions_2.yaml
bmi_ilamb/data/ilamb.cfg
bmi_ilamb/data/tropics.txt