Metadata-Version: 1.1
Name: bmi-ilamb
Version: 0.1.1
Summary: BMI for ILAMB
Home-page: https://github.com/permamodel/bmi-ilamb
Author: Mark Piper
Author-email: mark.piper@colorado.edu
License: MIT
Keywords: CSDMS BMI ILAMB model benchmark
Platform: UNKNOWN
Classifier: Development Status :: 3 - Alpha
Classifier: License :: OSI Approved :: MIT License
Classifier: Programming Language :: Python :: 2.7
